design/Control_Unit.v
module Control_Unit (control_opcode, reg_dst, jump, branch, mem_read, mem_to_reg, alu_op, mem_write, ALU_src, reg_write);
    input [2:0] control_opcode;
    output reg [1:0] alu_op;
    output reg reg_dst, jump, branch, reg_write,  mem_read, mem_to_reg, mem_write, ALU_src;
    parameter  LOAD_WORD_OPCODE = 3'b001,
                STORE_WORD_OPCODE = 3'b010,
                JUMP_OPCODE = 3'b011,
                ADD_OPCODE = 3'b100,
                ADD_IMMEDIATE_OPCODE = 3'b101,
                SUBTRACT_OPCODE = 3'b110;
    always @(*) begin
        case(control_opcode)
            LOAD_WORD_OPCODE:      
                begin
                    reg_dst <= 0;
                    reg_write <= 1;
                    branch <= 0;
                    jump <= 0;
                    alu_op <= 2'b00;
                    mem_read <= 1;
                    mem_write <= 0;
                    mem_to_reg <= 1;
                    ALU_src <= 1;
                end
            STORE_WORD_OPCODE:     
                begin
                    reg_dst <= 0;
                    reg_write <= 0;
                    branch <= 0;
                    jump <= 0;
                    alu_op <= 2'b00;
                    mem_read <= 0;
                    mem_write <= 1;
                    mem_to_reg <= 0;
                    ALU_src <= 1;                
                end
            JUMP_OPCODE :    
                begin
                    reg_dst <= 0;
                    reg_write <= 0;
                    branch <= 0;
                    jump <= 1;
                    alu_op <= 2'b01;
                    mem_read <= 0;
                    mem_write <= 0;
                    mem_to_reg <= 0;
                    ALU_src <= 0;
                end
            ADD_OPCODE:      
                begin
                    reg_dst <= 1;
                    reg_write <= 1;
                    branch <= 0;
                    jump <= 0;
                    alu_op <= 2'b10;
                    mem_read <= 0;
                    mem_write <= 0;
                    mem_to_reg <= 0;
                    ALU_src <= 0;
                end
            ADD_IMMEDIATE_OPCODE:     
                begin
                    reg_dst <= 0;
                    reg_write <= 1;
                    branch <= 0;
                    jump <= 0;
                    alu_op <= 2'b10;
                    mem_read <= 0;
                    mem_write <= 0;
                    mem_to_reg <= 0;
                    ALU_src <= 1;
                end
            SUBTRACT_OPCODE:      
                begin
                    reg_dst <= 1;
                    reg_write <= 1;
                    branch <= 0;
                    jump <= 0;
                    alu_op <= 2'b10;
                    mem_read <= 0;
                    mem_write <= 0;
                    mem_to_reg <= 0;
                    ALU_src <= 0;
                end
            endcase
        end
endmodule

testbench/Control_Unit_tb.v
`timescale 1ps/1ps
`include "../design/Control_Unit.v"

module Control_Unit_tb();
    reg [2:0] control_opcode;
    wire [1:0] alu_op;
    wire reg_dst, jump, branch, reg_write,  mem_read, mem_to_reg, mem_write, ALU_src;
    Control_Unit control_unit (.control_opcode(control_opcode), .reg_dst(reg_dst), .jump(jump), .branch(branch), .mem_read(mem_read), .mem_to_reg(mem_to_reg), .alu_op(alu_op), .mem_write(mem_write), .ALU_src(ALU_src), .reg_write(reg_write));
    initial
		begin
			$dumpfile("vcd/Control_Unit_dump.vcd");
			$dumpvars(0, Control_Unit_tb);
            #1;
            control_opcode = 3'b011;
            #5;	
            control_opcode = 3'b001;
            #5;
            control_opcode = 3'b010;
            #5;
            control_opcode = 3'b011;
            #5;
            control_opcode = 3'b100;
            #5;
            control_opcode = 3'b101;
            #5;
            control_opcode = 3'b110;	            		          
        end
endmodule

testbench/vcd/Control_Unit_dump.vcd
$date
	Tue Apr  5 05:14:55 2022
$end
$version
	Icarus Verilog
$end
$timescale
	1ps
$end
$scope module Control_Unit_tb $end
$var wire 1 ! reg_write $end
$var wire 1 " reg_dst $end
$var wire 1 # mem_write $end
$var wire 1 $ mem_to_reg $end
$var wire 1 % mem_read $end
$var wire 1 & jump $end
$var wire 1 ' branch $end
$var wire 2 ( alu_op [1:0] $end
$var wire 1 ) ALU_src $end
$var reg 3 * control_opcode [2:0] $end
$scope module control_unit $end
$var wire 3 + control_opcode [2:0] $end
$var reg 1 ) ALU_src $end
$var reg 2 , alu_op [1:0] $end
$var reg 1 ' branch $end
$var reg 1 & jump $end
$var reg 1 % mem_read $end
$var reg 1 $ mem_to_reg $end
$var reg 1 # mem_write $end
$var reg 1 " reg_dst $end
$var reg 1 ! reg_write $end
$upscope $end
$upscope $end
$enddefinitions $end
#0
$dumpvars
bx ,
bx +
bx *
x)
bx (
x'
x&
x%
x$
x#
x"
x!
$end
#1
0)
0$
0#
0%
b1 (
b1 ,
1&
0'
0!
0"
b11 *
b11 +
#6
1)
1$
1%
b0 (
b0 ,
0&
1!
b1 *
b1 +
#11
0$
1#
0%
0!
b10 *
b10 +
#16
0)
0#
b1 (
b1 ,
1&
b11 *
b11 +
#21
b10 (
b10 ,
0&
1!
1"
b100 *
b100 +
#26
1)
0"
b101 *
b101 +
#31
0)
1"
b110 *
b110 +
