new/Instruction_Memory.v
`timescale 1ns / 1ps

module Instruction_Memory (pc, instruction);   
    input [7:0] pc;
    output reg [7:0] instruction;
    reg [7:0] rom[255:0];    
    initial begin		          
        rom[0]= 8'b00111001;                          
    end    
    always @(pc)
        begin
            instruction <= rom[pc];
        end    
endmodule

testbench/instruction_memory_tb.v

`timescale 1ps/1ps
`include "../design/Instruction_Memory.v" 

module Instruction_Memory_tb();
      reg [7:0] pc;
      wire [7:0] instruction;                      
	  Instruction_Memory a3(.pc(pc), .instruction(instruction));
      initial
		begin
			$dumpfile("vcd/Instruction_Memory_dump.vcd");
			$dumpvars(0, Instruction_Memory_tb);
            #1;
			pc = 8'd0; 
            #5;
			pc = 8'd1; 
            #5;	
            pc = 8'd2; 
            #5;	
            pc = 8'd3; 
            #5;	
            pc = 8'd4; 
            #5;		
            pc = 8'd5; 
            #5;	
            pc = 8'd6; 
            #5;	
            pc = 8'd7; 
            #5;				            		         
		end        
endmodule

testbench/vcd/instruction_memory_dump.vcd
$date
	Tue Apr  5 04:40:24 2022
$end
$version
	Icarus Verilog
$end
$timescale
	1ps
$end
$scope module Instruction_Memory_tb $end
$var wire 8 ! instruction [7:0] $end
$var reg 8 " pc [7:0] $end
$scope module a3 $end
$var wire 8 # pc [7:0] $end
$var reg 8 $ instruction [7:0] $end
$upscope $end
$upscope $end
$enddefinitions $end
#0
$dumpvars
bx $
bx #
bx "
bx !
$end
#1
b11 !
b11 $
b0 "
b0 #
#6
b100 !
b100 $
b1 "
b1 #
#11
b110 !
b110 $
b10 "
b10 #
#16
b1001 !
b1001 $
b11 "
b11 #
#21
b10 !
b10 $
b100 "
b100 #
#26
b1010 !
b1010 $
b101 "
b101 #
#31
b111 !
b111 $
b110 "
b110 #
#36
b10101 !
b10101 $
b111 "
b111 #
